Metadata-Version: 1.0
Name: tiny2d
Version: 0.0.2
Summary: A python library for basic 2-D geometry.
Home-page: https://github.com/ngroup/tiny2d
Author: Chun Nien
Author-email: contact@chunnien.com
License: MIT
Platform: UNKNOWN
